LICENSE
MANIFEST.in
README.md
dev-requirements.txt
pyproject.toml
requirements.txt
setup.cfg
setup.py
versioneer.py
src/fidesops/__init__.py
src/fidesops/_version.py
src/fidesops/main.py
src/fidesops/py.typed
src/fidesops.egg-info/PKG-INFO
src/fidesops.egg-info/SOURCES.txt
src/fidesops.egg-info/dependency_links.txt
src/fidesops.egg-info/entry_points.txt
src/fidesops.egg-info/requires.txt
src/fidesops.egg-info/top_level.txt
src/fidesops/ops/__init__.py
src/fidesops/ops/alembic.ini
src/fidesops/ops/analytics.py
src/fidesops/ops/cli.py
src/fidesops/ops/common_exceptions.py
src/fidesops/ops/api/__init__.py
src/fidesops/ops/api/deps.py
src/fidesops/ops/api/v1/__init__.py
src/fidesops/ops/api/v1/api.py
src/fidesops/ops/api/v1/exception_handlers.py
src/fidesops/ops/api/v1/scope_registry.py
src/fidesops/ops/api/v1/urn_registry.py
src/fidesops/ops/api/v1/endpoints/__init__.py
src/fidesops/ops/api/v1/endpoints/config_endpoints.py
src/fidesops/ops/api/v1/endpoints/connection_endpoints.py
src/fidesops/ops/api/v1/endpoints/connection_type_endpoints.py
src/fidesops/ops/api/v1/endpoints/consent_request_endpoints.py
src/fidesops/ops/api/v1/endpoints/dataset_endpoints.py
src/fidesops/ops/api/v1/endpoints/drp_endpoints.py
src/fidesops/ops/api/v1/endpoints/email_endpoints.py
src/fidesops/ops/api/v1/endpoints/encryption_endpoints.py
src/fidesops/ops/api/v1/endpoints/health_endpoints.py
src/fidesops/ops/api/v1/endpoints/identity_verification_endpoints.py
src/fidesops/ops/api/v1/endpoints/manual_webhook_endpoints.py
src/fidesops/ops/api/v1/endpoints/masking_endpoints.py
src/fidesops/ops/api/v1/endpoints/oauth_endpoints.py
src/fidesops/ops/api/v1/endpoints/policy_endpoints.py
src/fidesops/ops/api/v1/endpoints/policy_webhook_endpoints.py
src/fidesops/ops/api/v1/endpoints/privacy_request_endpoints.py
src/fidesops/ops/api/v1/endpoints/saas_config_endpoints.py
src/fidesops/ops/api/v1/endpoints/storage_endpoints.py
src/fidesops/ops/api/v1/endpoints/user_endpoints.py
src/fidesops/ops/api/v1/endpoints/user_permission_endpoints.py
src/fidesops/ops/core/__init__.py
src/fidesops/ops/core/config.py
src/fidesops/ops/db/__init__.py
src/fidesops/ops/db/base.py
src/fidesops/ops/db/base_class.py
